LICENSE
nb_workflows/__init__.py
nb_workflows/__version__.py
nb_workflows/auth.py
nb_workflows/cli.py
nb_workflows/client/__init__.py
nb_workflows/client/agent.py
nb_workflows/client/agent_client.py
nb_workflows/client/base.py
nb_workflows/client/diskclient.py
nb_workflows/client/history_client.py
nb_workflows/client/init_script.py
nb_workflows/client/nbclient.py
nb_workflows/client/projects_client.py
nb_workflows/client/shortcuts.py
nb_workflows/client/state.py
nb_workflows/client/types.py
nb_workflows/client/uploads.py
nb_workflows/client/utils.py
nb_workflows/client/workflows_client.py
nb_workflows/cmd/__init__.py
nb_workflows/cmd/common.py
nb_workflows/cmd/executors.py
nb_workflows/cmd/history.py
nb_workflows/cmd/manager.py
nb_workflows/cmd/project.py
nb_workflows/cmd/services.py
nb_workflows/cmd/utils.py
nb_workflows/cmd/workflows.py
nb_workflows/conf/__init__.py
nb_workflows/conf/client_settings.py
nb_workflows/conf/defaults.py
nb_workflows/conf/global_client.py
nb_workflows/conf/global_settings.py
nb_workflows/conf/jtemplates.py
nb_workflows/conf/server_settings.py
nb_workflows/conf/templates/Dockerfile
nb_workflows/conf/templates/Makefile
nb_workflows/conf/templates/__init__.py
nb_workflows/conf/templates/client_settings.py.j2
nb_workflows/conf/templates/dockerignore
nb_workflows/conf/templates/gitignore
nb_workflows/conf/templates/settings.py.j2
nb_workflows/conf/templates/test_workflow.ipynb.j2
nb_workflows/conf/templates/welcome.ipynb.j2
nb_workflows/conf/types.py
nb_workflows/conf/utils.py
nb_workflows/core/__init__.py
nb_workflows/core/registers.py
nb_workflows/db/__init__.py
nb_workflows/db/alembic.ini
nb_workflows/db/common.py
nb_workflows/db/migrations/env.py
nb_workflows/db/migrations/script.py.mako
nb_workflows/db/migrations/versions/0000_init.py
nb_workflows/db/nosync.py
nb_workflows/db/sync.py
nb_workflows/db/utils.py
nb_workflows/errors/__init__.py
nb_workflows/errors/client.py
nb_workflows/errors/generics.py
nb_workflows/errors/projects.py
nb_workflows-0.7.0.dist-info/entry_points.txt
nb_workflows-0.7.0.dist-info/LICENSE
nb_workflows-0.7.0.dist-info/WHEEL
nb_workflows-0.7.0.dist-info/METADATA
nb_workflows-0.7.0.dist-info/RECORD
